README.md
setup.cfg
setup.py
sl_bndist/Binomialdistribution.py
sl_bndist/Gaussiandistribution.py
sl_bndist/Generaldistribution.py
sl_bndist/__init__.py
sl_bndist.egg-info/PKG-INFO
sl_bndist.egg-info/SOURCES.txt
sl_bndist.egg-info/dependency_links.txt
sl_bndist.egg-info/not-zip-safe
sl_bndist.egg-info/top_level.txt