Metadata-Version: 1.0
Name: sl-bndist
Version: 0.1
Summary: Gaussian and Binomial distributions
Home-page: UNKNOWN
Author: Sudhanva Lalit
Author-email: sudsid@gmail.com
License: UNKNOWN
Platform: UNKNOWN
